GeiMeiziJiangPythonDierji/README.md
GeiMeiziJiangPythonDierji/__init__.py
GeiMeiziJiangPythonDierji/__main__.py
GeiMeiziJiangPythonDierji/file.epub
GeiMeiziJiangPythonDierji/index.html
GeiMeiziJiangPythonDierji/css/__init__.py
GeiMeiziJiangPythonDierji/css/annotations.css
GeiMeiziJiangPythonDierji/css/main.css
GeiMeiziJiangPythonDierji/css/normalize.css
GeiMeiziJiangPythonDierji/css/popup.css
GeiMeiziJiangPythonDierji/font/__init__.py
GeiMeiziJiangPythonDierji/font/fontello.eot
GeiMeiziJiangPythonDierji/font/fontello.svg
GeiMeiziJiangPythonDierji/font/fontello.ttf
GeiMeiziJiangPythonDierji/font/fontello.woff
GeiMeiziJiangPythonDierji/img/__init__.py
GeiMeiziJiangPythonDierji/img/annotator-glyph-sprite.png
GeiMeiziJiangPythonDierji/img/annotator-icon-sprite.png
GeiMeiziJiangPythonDierji/img/apple-touch-icon.png
GeiMeiziJiangPythonDierji/img/cancelfullscreen.png
GeiMeiziJiangPythonDierji/img/close.png
GeiMeiziJiangPythonDierji/img/fullscreen.png
GeiMeiziJiangPythonDierji/img/loader.gif
GeiMeiziJiangPythonDierji/img/menu-icon.png
GeiMeiziJiangPythonDierji/img/save.png
GeiMeiziJiangPythonDierji/img/saved.png
GeiMeiziJiangPythonDierji/img/settings-s.png
GeiMeiziJiangPythonDierji/img/settings.png
GeiMeiziJiangPythonDierji/img/star.png
GeiMeiziJiangPythonDierji/js/__init__.py
GeiMeiziJiangPythonDierji/js/epub.js
GeiMeiziJiangPythonDierji/js/epub.min.js
GeiMeiziJiangPythonDierji/js/epub.min.map
GeiMeiziJiangPythonDierji/js/hooks.min.js
GeiMeiziJiangPythonDierji/js/hooks.min.map
GeiMeiziJiangPythonDierji/js/reader.js
GeiMeiziJiangPythonDierji/js/reader.js.map
GeiMeiziJiangPythonDierji/js/reader.min.js
GeiMeiziJiangPythonDierji/js/reader.min.map
GeiMeiziJiangPythonDierji/js/hooks/__init__.py
GeiMeiziJiangPythonDierji/js/hooks/extensions/__init__.py
GeiMeiziJiangPythonDierji/js/hooks/extensions/highlight.js
GeiMeiziJiangPythonDierji/js/libs/__init__.py
GeiMeiziJiangPythonDierji/js/libs/jquery.min.js
GeiMeiziJiangPythonDierji/js/libs/localforage.min.js
gei_meizi_jiang_python_dierji-2024.3.4.0.dist-info/METADATA
gei_meizi_jiang_python_dierji-2024.3.4.0.dist-info/WHEEL
gei_meizi_jiang_python_dierji-2024.3.4.0.dist-info/entry_points.txt
gei_meizi_jiang_python_dierji-2024.3.4.0.dist-info/top_level.txt
gei_meizi_jiang_python_dierji-2024.3.4.0.dist-info/RECORD
